{
  "kind": "singleType",
  "collectionName": "legislative_activity_pages",
  "info": {
    "singularName": "legislative-activity-page",
    "pluralName": "legislative-activity-pages",
    "displayName": "Страница закон. деятельность",
    "description": ""
  },
  "options": {
    "draftAndPublish": true
  },
  "pluginOptions": {
    "i18n": {
      "localized": true
    }
  },
  "attributes": {
    "content": {
      "type": "richtext",
      "pluginOptions": {
        "i18n": {
          "localized": true
        }
      }
    },
    "seo": {
      "type": "component",
      "repeatable": false,
      "component": "seo.seo",
      "pluginOptions": {
        "i18n": {
          "localized": true
        }
      }
    }
  }
}
